ansi_image/__init__.py
ansi_image/algorithms.py
ansi_image/ansi_image.py
ansi_image/tables.py
ansi_image/tools/__init__.py
ansi_image/tools/print.py
ansi_image-0.1.0.dist-info/METADATA
ansi_image-0.1.0.dist-info/WHEEL
ansi_image-0.1.0.dist-info/entry_points.txt
ansi_image-0.1.0.dist-info/licenses/LICENSE
ansi_image-0.1.0.dist-info/RECORD
