Metadata-Version: 2.4
Name: ansi-image
Version: 0.1.0
Summary: A library and tool for displaying images in the terminal using ANSI color codes
Author-email: Benno Evers <benno.martin.evers@gmail.com>
License:                                  Apache License
License-File: LICENSE
Keywords: ansi,cli,image,terminal,viewer
Classifier: Development Status :: 4 - Beta
Classifier: Environment :: Console
Classifier: Intended Audience :: Developers
Classifier: License :: OSI Approved :: MIT License
Classifier: Operating System :: OS Independent
Classifier: Programming Language :: Python :: 3
Classifier: Programming Language :: Python :: 3.13
Classifier: Topic :: Multimedia :: Graphics :: Viewers
Classifier: Topic :: System :: Shells
Classifier: Topic :: Terminals
Requires-Python: >=3.13
Requires-Dist: pillow>=11.1.0
Requires-Dist: pydantic>=2.11.7
